{"cameraMode":{"drawMode":0,"name":"Shaded","section":"Shading Mode"},"sceneLighting":false,"audioPlay":false,"sceneViewState":{"m_AlwaysRefresh":false,"showFog":true,"showSkybox":false,"showFlares":true,"showImageEffects":true,"showParticleSystems":true,"showVisualEffectGraphs":true,"m_FxEnabled":true},"in2DMode":false,"pivot":{"x":-3.380000114440918,"y":0.0,"z":0.0},"rotation":{"x":0.07353685796260834,"y":0.09126318246126175,"z":-0.0004595176433213055,"w":0.9931420087814331},"size":3.6679165363311769,"orthographic":false}